setup.py
bin/pyNES
bin/pynes
pyNES.egg-info/SOURCES.txt
pynes/__init__.py
pynes/analyzer.py
pynes/bitbag.py
pynes/c6502.py
pynes/cartridge.py
pynes/compiler.py
pynes/directives.py
pynes/image.py
pynes/nametable.py
pynes/python.py
pynes/sdk.py
pynes/sprite.py
pynes.egg-info/PKG-INFO
pynes.egg-info/SOURCES.txt
pynes.egg-info/dependency_links.txt
pynes.egg-info/top_level.txt
pynes/examples/__init__.py
pynes/examples/helloworld.py
pynes/examples/movingsprite.py
pynes/examples/proposal.py
pynes/examples/roulette.py
pynes/examples/test.py