Metadata-Version: 1.0
Name: pyNES
Version: 0.1.1
Summary: Python Programming for Nintendo 8bits
Home-page: http://github.com/gutomaia/pyNES/
Author: Gustavo Maia Neto (Guto Maia)
Author-email: guto@guto.net
License: GPL3
Platform: UNKNOWN
Classifier: Development Status :: 4 - Beta
Classifier: Environment :: Console
Classifier: Programming Language :: Assembly
Classifier: Topic :: Games/Entertainment
Classifier: Topic :: Software Development :: Assemblers
Classifier: Topic :: Software Development :: Build Tools
Classifier: Topic :: Software Development :: Compilers
Classifier: Topic :: Software Development :: Embedded Systems
